remote/__init__.py
remote/__main__.py
remote/config.py
remote/models.py
remote/statics/buttons.js
remote/statics/style.css
remote/templates/index.html
couch_remote-0.2.2.dist-info/LICENSE
couch_remote-0.2.2.dist-info/METADATA
couch_remote-0.2.2.dist-info/WHEEL
couch_remote-0.2.2.dist-info/entry_points.txt
couch_remote-0.2.2.dist-info/top_level.txt
couch_remote-0.2.2.dist-info/RECORD
