Metadata-Version: 2.1
Name: couch-remote
Version: 0.2.2
Summary: A simple remote web keyboard
Author-email: Sorebit <tomulewicz.s@pm.me>
License: MIT License
Project-URL: Homepage, https://github.com/sorebit/couch-remote
Keywords: remote,keyboard,couch
Classifier: License :: OSI Approved :: MIT License
Classifier: Programming Language :: Python
Classifier: Programming Language :: Python :: 3
Classifier: Development Status :: 3 - Alpha
Classifier: Environment :: Console
Classifier: Environment :: Web Environment
Classifier: Framework :: FastAPI
Classifier: Intended Audience :: End Users/Desktop
Classifier: Natural Language :: English
Classifier: Operating System :: OS Independent
Classifier: Topic :: Home Automation
Classifier: Topic :: Utilities
Requires-Python: >=3.8
License-File: LICENSE
Requires-Dist: FastAPI (>=0.79.0)
Requires-Dist: uvicorn[standard] (>=0.18.0)
Requires-Dist: pydantic (<2.0.0,>=1.9.0)
Requires-Dist: jinja2 (>=3.1.2)
Requires-Dist: pynput (>=1.7.6)
Provides-Extra: dev
Requires-Dist: black ; extra == 'dev'
Requires-Dist: bumpver ; extra == 'dev'
Requires-Dist: isort ; extra == 'dev'
Requires-Dist: pip-tools ; extra == 'dev'
Requires-Dist: pytest ; extra == 'dev'
